LICENSE
README.md
setup.py
llm_router/__init__.py
llm_router/chroma.py
llm_router.egg-info/PKG-INFO
llm_router.egg-info/SOURCES.txt
llm_router.egg-info/dependency_links.txt
llm_router.egg-info/requires.txt
llm_router.egg-info/top_level.txt
test/test_router.py