Metadata-Version: 2.1
Name: llm-router
Version: 0.1.1
Summary: Quick LLM routing using Embeddings
Author: herval
Author-email: hervalfreire@gmail.com
Classifier: Programming Language :: Python :: 3
Classifier: License :: OSI Approved :: MIT License
Classifier: Operating System :: OS Independent
Requires-Python: >=3.9
License-File: LICENSE
